pyrobird/__init__.py
pyrobird/__version__.py
pyrobird/cern_root.py
pyrobird/dex_utils.py
pyrobird/edm4eic.py
pyrobird/utils.py
pyrobird/cli/__init__.py
pyrobird/cli/__main__.py
pyrobird/cli/convert.py
pyrobird/cli/geo.py
pyrobird/cli/merge.py
pyrobird/cli/screenshot.py
pyrobird/cli/serve.py
pyrobird/cli/smooth.py
pyrobird/data/eic_geo_process_rules.yaml
pyrobird/server/__init__.py
pyrobird-0.2.7.dist-info/licenses/LICENSE
pyrobird-0.2.7.dist-info/METADATA
pyrobird-0.2.7.dist-info/WHEEL
pyrobird-0.2.7.dist-info/entry_points.txt
pyrobird-0.2.7.dist-info/top_level.txt
pyrobird-0.2.7.dist-info/RECORD
