Metadata-Version: 2.4
Name: pyrobird
Version: 0.2.7
Summary: pyrobird is a python backend for Firebird HENP event display
Author-email: Dmitry Romanov <romanovda@gmail.com>
License:                    GNU LESSER GENERAL PUBLIC LICENSE
Classifier: Development Status :: 4 - Beta
Classifier: License :: OSI Approved :: GNU Lesser General Public License v3 or later (LGPLv3+)
Classifier: Programming Language :: Python
Classifier: Programming Language :: Python :: 3.8
Classifier: Programming Language :: Python :: 3.9
Classifier: Programming Language :: Python :: 3.10
Classifier: Programming Language :: Python :: 3.11
Classifier: Programming Language :: Python :: 3.12
Classifier: Programming Language :: Python :: Implementation :: CPython
Classifier: Programming Language :: Python :: Implementation :: PyPy
Requires-Python: >=3.8
License-File: LICENSE
Requires-Dist: click
Requires-Dist: rich
Requires-Dist: pyyaml
Requires-Dist: flask
Requires-Dist: flask-cors
Requires-Dist: flask-compress>=1.8.0
Requires-Dist: json5
Requires-Dist: uproot
Provides-Extra: batch
Requires-Dist: playwright; extra == "batch"
Provides-Extra: xrootd
Requires-Dist: fsspec-xrootd; extra == "xrootd"
Requires-Dist: xrootd; extra == "xrootd"
Provides-Extra: dev
Requires-Dist: build>=0.10.0; extra == "dev"
Requires-Dist: twine>=4.0.0; extra == "dev"
Requires-Dist: coverage>=6.5.0; extra == "dev"
Provides-Extra: test
Requires-Dist: pytest>=7.0.0; extra == "test"
Dynamic: license-file
